<?xml version="1.0" encoding="utf-8" ?>
<dwsync>
<file name="Brave.pdf" server="ftp.fadee.x10.mx/public_html/mrkannah.com/new/" local="129656267225773011" remote="129847153200000000" Dst="2" />
<file name="com.pdf" server="ftp.fadee.x10.mx/public_html/mrkannah.com/new/" local="129708073781859801" remote="129847153200000000" Dst="2" />
<file name="deans.pdf" server="ftp.fadee.x10.mx/public_html/mrkannah.com/new/" local="129826423564400036" remote="129847153800000000" Dst="2" />
<file name="director.pdf" server="ftp.fadee.x10.mx/public_html/mrkannah.com/new/" local="129826493067542514" remote="129847153800000000" Dst="2" />
<file name="JA.pdf" server="ftp.fadee.x10.mx/public_html/mrkannah.com/new/" local="129708071636046670" remote="129847153800000000" Dst="2" />
<file name="mep.pdf" server="ftp.fadee.x10.mx/public_html/mrkannah.com/new/" local="129826472884838218" remote="129847154400000000" Dst="2" />
<file name="LSAMP.pdf" server="ftp.fadee.x10.mx/public_html/mrkannah.com/new/" local="129826449571294877" remote="129847154400000000" Dst="2" />
<file name="PIQE.pdf" server="ftp.fadee.x10.mx/public_html/mrkannah.com/new/" local="129708067905110131" remote="129847154400000000" Dst="2" />
<file name="olympics.pdf" server="ftp.fadee.x10.mx/public_html/mrkannah.com/new/" local="129826459282490248" remote="129847154400000000" Dst="2" />
<file name="resume.doc" server="ftp.fadee.x10.mx/public_html/mrkannah.com/new/" local="129826415862130000" remote="129847154400000000" Dst="2" />
<file name="pull.pdf" server="ftp.fadee.x10.mx/public_html/mrkannah.com/new/" local="129708069014932013" remote="129847154400000000" Dst="2" />
<file name="resume.pdf" server="ftp.fadee.x10.mx/public_html/mrkannah.com/new/" local="129826414605537630" remote="129847155000000000" Dst="2" />
<file name="ROPs.pdf" server="ftp.fadee.x10.mx/public_html/mrkannah.com/new/" local="129656952766166574" remote="129847155000000000" Dst="2" />
<file name="ROP.pdf" server="ftp.fadee.x10.mx/public_html/mrkannah.com/new/" local="129656949880776699" remote="129847155600000000" Dst="2" />
</dwsync>